MANIFEST.in
README.md
setup.py
cordy/__init__.py
cordy/logging.py
cordy/utils.py
cordy.egg-info/PKG-INFO
cordy.egg-info/SOURCES.txt
cordy.egg-info/dependency_links.txt
cordy.egg-info/requires.txt
cordy.egg-info/top_level.txt
cordy/auth/__init__.py
cordy/auth/controllers.py
cordy/auth/decorators.py
cordy/auth/hashers.py
cordy/auth/middlewares.py
cordy/auth/models.py
cordy/auth/permissions.py
cordy/auth/serializers.py
cordy/base/__init__.py
cordy/base/decorators.py
cordy/base/exceptions.py
cordy/base/management.py
cordy/conf/__init__.py
cordy/conf/default.py
cordy/crud/__init__.py
cordy/crud/controllers.py
cordy/crud/filters.py
cordy/crud/pagination.py
cordy/db/__init__.py
cordy/db/base.py
cordy/db/migrations.py
cordy/db/models.py
cordy/http/__init__.py
cordy/http/exceptions.py
cordy/http/json_api_parser.py
cordy/http/parser.py
cordy/http/responses.py
cordy/management/__init__.py
cordy/management/createuser.py
cordy/management/migrate.py
cordy/management/runserver.py
cordy/management/shell.py
cordy/middlewares/__init__.py
cordy/middlewares/cors.py
cordy/middlewares/session.py
cordy/pages/__init__.py
cordy/pages/models.py
cordy/resolvers/__init__.py
cordy/templates/__init__.py
cordy/templates/_interface_vars.html
cordy/templates/base.html
cordy/templates/crud/__init__.py
cordy/templates/crud/base.html
cordy/templates/crud/get.html
cordy/templates/crud/index.html
cordy/templates/crud/new-bak.html
cordy/templates/crud/new.html
cordy/templates/crud/swagger-ui.html
cordy/templates/crud/fields/__init__.py
cordy/templates/crud/fields/boolean.html
cordy/testing/__init__.py
cordy/testing/uwsgi_mock.py
cordy/xsrf/__init__.py
cordy/xsrf/decorators.py
cordy/xsrf/exceptions.py
cordy/xsrf/middlewares.py
myapp/__init__.py
myapp/controllers.py
myapp/models.py
myapp/migrations/0001_initial.py
myapp/migrations/__init__.py
public/__init__.py
public/manage.py